filtermui/__init__.py
filtermui/django_filter_operators.py
filtermui/filter_types.py
filtermui/filtermui.py
filtermui-1.0.0.dist-info/LICENSE
filtermui-1.0.0.dist-info/METADATA
filtermui-1.0.0.dist-info/WHEEL
filtermui-1.0.0.dist-info/top_level.txt
filtermui-1.0.0.dist-info/RECORD
