Metadata-Version: 2.1
Name: filtermui
Version: 1.0.0
Summary: Converts MUI filters into a Django query.
Home-page: https://github.com/maxlaza411/filter-mui
Author: William Lazarre
Author-email: maxlazarr@gmail.com
License: UNKNOWN
Project-URL: Bug Tracker, https://github.com/maxlaza411/filter-mui/issues
Platform: UNKNOWN
Classifier: Programming Language :: Python :: 3
Classifier: License :: OSI Approved :: MIT License
Classifier: Operating System :: OS Independent
Requires-Python: >=3.9
License-File: LICENSE
